Metadata-Version: 2.1
Name: cookie-sync
Version: 0.0.1
Summary: Sync cookies between Chrome
Home-page: https://github.com/Sunney-X/cookie-sync
Author: Sunney-X
Author-email: sunneyxdev@gmail.com
License: UNKNOWN
Platform: UNKNOWN
